Metadata-Version: 2.1
Name: evase-analysis
Version: 1.0.8.5
Summary: A Python package with tools for the detection of SQL injection vulnerabilities in projects.
Author-email: Tony Abou Zeidan <tony.azp25@gmail.com>, Anthony Dooley <anthonydooley@cmail.carleton.ca>, Ethan Chase <e281828c@gmail.com>, Shaopeng Liu <shaopengliu@cmail.carleton.ca>, Jason Jaskolka <jason.jaskolka@carleton.ca>
Maintainer-email: Tony Abou Zeidan <tony.azp25@gmail.com>, Anthony Dooley <anthonydooley@cmail.carleton.ca>, Ethan Chase <e281828c@gmail.com>, Shaopeng Liu <shaopengliu@cmail.carleton.ca>, Jason Jaskolka <jason.jaskolka@carleton.ca>
Keywords: attack,security,SQL,injection
Classifier: Programming Language :: Python :: 3 :: Only
Classifier: Programming Language :: Python :: 3
Requires-Python: >=3.7
Requires-Dist: Flask (~=2.2.2)
Requires-Dist: Jinja2 (~=3.1.2)
Requires-Dist: networkx (~=2.8.8)
Requires-Dist: matplotlib (~=3.7.1)
